{
  "providers": [
    {
      "id": "piaoyun",
      "name": "派欧云",
      "type": "multi",
      "models": [
        {
          "id": "seedream-4.0",
          "name": "即梦图片生成 4.0",
          "type": "image",
          "description": "先进的图像生成模型，支持4K分辨率",
          "functions": [
            "图片生成",
            "图片编辑"
          ]
        },
        {
          "id": "vidu-q1",
          "name": "Vidu Q1",
          "type": "video",
          "description": "支持文/图生视频、首尾帧、参考生视频多种模式",
          "functions": [
            "文生视频",
            "图生视频",
            "首尾帧",
            "参考生视频"
          ]
        },
        {
          "id": "kling-2.5-turbo",
          "name": "可灵 V2.5 Turbo",
          "type": "video",
          "description": "文生/图生视频，支持宽高比与负面提示",
          "functions": [
            "文生视频",
            "图生视频"
          ]
        },
        {
          "id": "minimax-hailuo-2.3",
          "name": "Minimax Hailuo 2.3",
          "type": "video",
          "description": "文生/图生视频，分辨率与时长受限",
          "functions": [
            "文生视频",
            "图生视频"
          ]
        },
        {
          "id": "minimax-hailuo-02",
          "name": "Minimax Hailuo-02",
          "type": "video",
          "description": "文生/图生/首尾帧；6/10 秒与 768P/1080P",
          "functions": [
            "文生视频",
            "图生视频",
            "首尾帧"
          ]
        },
        {
          "id": "pixverse-v4.5",
          "name": "PixVerse V4.5",
          "type": "video",
          "description": "文生/图生视频，支持 fast_mode 与风格",
          "functions": [
            "文生视频",
            "图生视频"
          ]
        },
        {
          "id": "wan-2.5-preview",
          "name": "Wan 2.5 Preview",
          "type": "video",
          "description": "文生/图生视频，支持音频与水印选项",
          "functions": [
            "文生视频",
            "图生视频"
          ]
        },
        {
          "id": "seedance-v1",
          "name": "Seedance V1 (Lite/Pro)",
          "type": "video",
          "description": "文/图生视频，480p/720p/1080p，支持相机固定；Lite 支持首尾图",
          "functions": [
            "文生视频",
            "图生视频",
            "首尾帧"
          ]
        },
        {
          "id": "minimax-speech-2.6",
          "name": "MiniMax Speech-2.6",
          "type": "audio",
          "description": "同步语音合成（HD/Turbo）",
          "functions": [
            "语音合成"
          ]
        }
      ]
    },
    {
      "id": "fal",
      "name": "fal",
      "type": "multi",
      "models": [
        {
          "id": "nano-banana",
          "name": "Nano Banana",
          "type": "image",
          "description": "Google 最先进的图像生成和编辑模型",
          "functions": [
            "图片生成",
            "图片编辑"
          ]
        }
      ]
    }
  ]
}